Workbook

Sheet Analisis de Ingresos
A1: 1 | C1: EXPERIENCIA
A2: Sigla | B2: Rol | C2: .- 2 años | D2: .+ 2 años | E2: Sueldo Liquido | F2: Sueldo Costo Empresa | G2: HH
A3: JP | B3: Jefe de proyecto | C3: X | E3: 1800000 | F3: =(E3*19/100)+E3 -> 2142000 | G3: =F3/160 -> 13387.5 | I3: https://cl.talent.com/salary?job=Jefe+de+proyecto
A4: AP | B4: ANALISTA DE PROCESOS | C4: X | E4: 800000 | F4: =(E4*19/100)+E4 -> 952000 | G4: =F4/160 -> 5950 | I4: https://cl.talent.com/salary?job=analista+de+procesos
A5: ASW | B5: ARQUITECTO DE SOFTWARE | C5: X | E5: 1500000 | F5: =(E5*19/100)+E5 -> 1785000 | G5: =F5/160 -> 11156.25
A6: DBA | B6: ADMINISTRADOR DE BBDD | C6: X | E6: 1350000 | F6: =(E6*19/100)+E6 -> 1606500 | G6: =F6/160 -> 10040.625
A7: PFS 1 | B7: PROGRAMADOR FULL STACK | C7: X | E7: 1000000 | F7: =(E7*19/100)+E7 -> 1190000 | G7: =F7/160 -> 7437.5
A8: PFS 2 | B8: PROGRAMADOR FULL STACK | C8: X | E8: 1300000 | F8: =(E8*19/100)+E8 -> 1547000 | G8: =F8/160 -> 9668.75 | I8: https://cl.talent.com/salary?job=programador+full+stack
A10: Sueldos referenciales de mercado (talent.com), usados solo para valorizar las horas de la hoja EDT v.
A11: Somos dos personas: Vicente Rivera cubre JP, ASW, DBA y PFS 1; Ignacio Fuenzalida cubre AP y PFS 2.

Sheet Carta Gantt
A1: Actividades Proyecto | B1: 1 | C1: 2 | D1: 3 | E1: 4 | F1: 5 | G1: 6 | H1: 7 | I1: 8 | J1: 9 | K1: 10 | L1: 11 | M1: 12 | N1: 13
A2: Semana 1 = 11/09/2026 (cada columna es una semana) | B2: Sept. | E2: Octubre | J2: Noviembre | N2: Dic.
A3: Fase 1: Planificación inicial
A4: Inicio del proyecto y confirmación del alcance validado
A5: Acta de Constitución del Proyecto
A6: EDT, Hitos de Desarrollo y Diccionario
A7: Carta Gantt, Matriz RACI y Matriz de Riesgos
A8: Plan de Pruebas Inicial (estrategia y matriz de casos)
A9: Fase 2: Análisis y diseño
A10: ERS y criterios de aceptación
A11: Ajuste de requerimientos al alcance actualizado (Queda / No queda)
A12: Modelo de datos: DER, tabla payouts, RLS y policies
A13: Arquitectura: Supabase (GoTrue, PostgREST), FastAPI y despliegue
A14: Mockups de interfaz Vue.js (cliente, productor y administración)
... A51: Control de calidad y revisión cruzada entre ambos

Sheet EDT v
A1: Proyecto: CuTuCo (Cultiva Tu Compra) - Marketplace SaaS B2B2C de comercio de proximidad | J1: DICCIONARIO EDT
B2: Días | C2: Horas por Actividad o Entregable | J2: SIGLA | K2: ROL | L2: NOMBRE | M2: COSTO x HORA
A3: Fase 1: Planificación inicial (Semana 1) | B3: =SUM(B4:B7) -> 5 | C3: JP | D3: AP | E3: ASW | F3: DBA | G3: PFS 1 | H3: PFS 2 | J3: JP | K3: JEFE DE PROYECTO | L3: Vicente Rivera | M3: ='Analisis de Ingresos'!G3 -> 13387.5
A4: 1.1 Inicio y alcance validado (objetivo, alcance, fuera de alcance) | B4: 1 | C4: 4 | D4: 3 | E4: 0 | F4: 0 | G4: 0 | H4: 0 | J4: AP | K4: ANALISTA DE PROCESOS | L4: Ignacio Fuenzalida | M4: ='Analisis de Ingresos'!G4 -> 5950
A5: 1.2 Acta de Constitución, EDT, Hitos de Desarrollo y Diccionario | B5: 2 | C5: 8 | D5: 6 | E5: 2 | F5: 0 | G5: 0 | H5: 0 | J5: ASW | K5: ARQUITECTO DE SOFTWARE | L5: Vicente Rivera | M5: ='Analisis de Ingresos'!G5 -> 11156.25
A6: 1.3 Carta Gantt, Matriz RACI y Matriz de Riesgos | B6: 1 | C6: 4 | D6: 3 | E6: 0 | F6: 0 | G6: 0 | H6: 0 | J6: DBA | K6: ADMINISTRADOR DE BBDD | L6: Vicente Rivera | M6: ='Analisis de Ingresos'!G6 -> 10040.625
A7: 1.4 Plan de Pruebas Inicial (estrategia y matriz de casos) | B7: 1 | C7: 2 | D7: 5 | E7: 0 | F7: 0 | G7: 2 | H7: 2 | J7: PFS 1 | K7: PROGRAMADOR FULL STACK | L7: Vicente Rivera | M7: ='Analisis de Ingresos'!G7 -> 7437.5
A8: Fase 2: Análisis y diseño (Semanas 2 a 4) | B8: =SUM(B9:B12) -> 10 | C8: JP | D8: AP | E8: ASW | F8: DBA | G8: PFS 1 | H8: PFS 2 | J8: PFS 2 | K8: PROGRAMADOR FULL STACK | L8: Ignacio Fuenzalida | M8: ='Analisis de Ingresos'!G8 -> 9668.75
A9: 2.1 ERS, criterios de aceptación y ajuste de requerimientos (Queda / No queda) | B9: 3 | C9: 6 | D9: 12 | E9: 4 | F9: 0 | G9: 4 | H9: 4
A10: 2.2 Modelo de datos (DER, payouts, RLS) y arquitectura de la solución | B10: 3 | C10: 4 | D10: 0 | E10: 14 | F10: 16 | G10: 4 | H10: 2
A11: 2.3 Mockups Vue.js: cliente, productor, administración, checkout y entrega | B11: 2 | C11: 2 | D11: 12 | E11: 0 | F11: 0 | G11: 0 | H11: 10
A12: 2.4 Plan de Calidad y de Costos; diseño de casos de prueba | B12: 2 | C12: 6 | D12: 8 | E12: 2 | F12: 0 | G12: 2 | H12: 2
A13: Fase 3: Construcción (Semanas 4 a 10) | B13: =SUM(B14:B19) -> 35 | C13: JP | D13: AP | E13: ASW | F13: DBA | G13: PFS 1 | H13: PFS 2
A14: 3.1 Base técnica: Git, FastAPI + Docker, Cloud Run, Supabase y Vue + Vite | B14: 5 | C14: 4 | D14: 0 | E14: 6 | F14: 4 | G14: 14 | H14: 12
A15: 3.2 Migración SQLite a PostgreSQL, DDL, RLS y autenticación con GoTrue | B15: 5 | C15: 3 | D15: 0 | E15: 4 | F15: 20 | G15: 14 | H15: 6
A16: 3.3 Catálogo invitado, carrito, registro, panel productor y CRUD base (PostgREST) | B16: 7 | C16: 3 | D16: 0 | E16: 2 | F16: 4 | G16: 14 | H16: 36
A17: 3.4 Webpay Plus Test, custodia, payouts manuales, reembolsos y checkout | B17: 6 | C17: 4 | D17: 0 | E17: 2 | F17: 6 | G17: 26 | H17: 12
A18: 3.5 Entrega con código, venta por región, calificaciones, sanciones y correos | B18: 6 | C18: 3 | D18: 0 | E18: 0 | F18: 2 | G18: 22 | H18: 18
A19: 3.6 Dashboard admin, validaciones (Vuelidate) y pruebas unitarias | B19: 6 | C19: 3 | D19: 4 | E19: 0 | F19: 0 | G19: 8 | H19: 24 | J19: COSTO HH POR ROL
A20: Fase 4: Implementación y cierre (Semanas 11 a 13) | B20: =SUM(B21:B24) -> 15 | C20: JP | D20: AP | E20: ASW | F20: DBA | G20: PFS 1 | H20: PFS 2 | J20: JP | K20: =$M$3*C26 -> 990675
A21: 4.1 Pruebas de integración API y E2E, correcciones y verificación de alcances | B21: 5 | C21: 4 | D21: 14 | E21: 0 | F21: 0 | G21: 14 | H21: 14 | J21: AP | K21: =$M$4*D26 -> 541450
A22: 4.2 Despliegue final (Vercel, Cloud Run, Supabase) y pruebas de humo | B22: 2 | C22: 2 | D22: 0 | E22: 2 | F22: 2 | G22: 6 | H22: 4 | J22: ASW | K22: =$M$5*E26 -> 446250
A23: 4.3 Plan de Implantación, Soporte y Mantenimiento; Manuales de Usuario/Admin | B23: 3 | C23: 4 | D23: 14 | E23: 2 | F23: 2 | G23: 4 | H23: 8 | J23: DBA | K23: =$M$6*F26 -> 562275
A24: 4.4 Plan de Pruebas Final, Reporte de Estatus Final y entrega final | B24: 5 | C24: 8 | D24: 10 | E24: 0 | F24: 0 | G24: 4 | H24: 4 | J24: PFS 1 | K24: =$M$7*G26 -> 1026375
B25: Dias | C25: JP | D25: AP | E25: ASW | F25: DBA | G25: PFS 1 | H25: PFS 2 | J25: PFS 2 | K25: =$M$8*H26 -> 1527662.5
A26: Total | B26: =B3+B8+B13+B20 -> 65 | C26: =SUM(C4:C7)+SUM(C9:C12)+SUM(C14:C19)+SUM(C21:C24) -> 74 | D26: =SUM(D4:D7)+SUM(D9:D12)+SUM(D14:D19)+SUM(D21:D24) -> 91 | E26: =SUM(E4:E7)+SUM(E9:E12)+SUM(E14:E19)+SUM(E21:E24) -> 40 | F26: =SUM(F4:F7)+SUM(F9:F12)+SUM(F14:F19)+SUM(F21:F24) -> 56 | G26: =SUM(G4:G7)+SUM(G9:G12)+SUM(G14:G19)+SUM(G21:G24) -> 138 | H26: =SUM(H4:H7)+SUM(H9:H12)+SUM(H14:H19)+SUM(H21:H24) -> 158 | J26: TOTAL HH | K26: =SUM(K20:K25) -> 5094687.5
A28: Notas del equipo:
A29: Somos dos personas: Vicente Rivera (líder backend / Jefe de Proyecto) e Ignacio Fuenzalida (IT frontend).
A30: Los roles de la tabla son funciones. Vicente cubre JP, ASW, DBA y PFS 1 (backend); Ignacio cubre AP y PFS 2 (frontend).
A31: Días hábiles: suman 65 (13 semanas desde el 11/09/2026). Las horas son estimaciones nuestras.
A32: El costo por hora usa sueldos referenciales (hoja Analisis de Ingresos); no son pagos reales del proyecto.
A33: Alcance actualizado: no planificamos historial de precios, stock bajo, múltiples admins, retención de carnet ni rate limiting.
A34: Sin geolocalización, fotos obligatorias ni cosecha del día: la entrega se confirma con código y las sanciones son manuales.
