Workbook

Sheet Alto Presupuesto
B1: PRESUPUESTO ESTIMADO – ESCENARIO ALTO – PLAN DE COSTOS
B2: CuTuCo (Cultiva Tu Compra) – Marketplace SaaS B2B2C | Duoc UC Plaza Norte – Ingeniería en Informática
B3: Duración: 13 semanas (11/09/2026 – 10/12/2026) | Equipo: Vicente Rivera e Ignacio Fuenzalida | Moneda: pesos chilenos (CLP)
B4: Opción B: infraestructura productiva con redundancia, cumplimiento y revisión de seguridad externa. Mayor dedicación del equipo.
B5: SUPUESTOS (celdas azules con fondo amarillo = editables)
B6: Tipo de cambio (CLP por USD) | C6: 950 | D6: Supuesto del equipo; ajustar al valor del día de pago.
B7: Duración del proyecto (meses) | C7: 3 | D7: 13 semanas ≈ 3 meses.
B8: Semanas de trabajo | C8: 13 | D8: Acta de Constitución: semanas 1 a 13.
B9: Horas por semana por integrante | C9: 28 | D9: Dedicación estimada compatible con la carga académica.
B10: Contingencia sobre el subtotal | C10: 0.2 | D10: Reserva alta por integraciones reales (Webpay) y revisión externa.
B11: Valor de un notebook propio (CLP) | C11: 1000000 | D11: Estimación de mercado Chile.
B12: Vida útil del notebook (meses) | C12: 36 | D12: Depreciación lineal.
B13: Estado de cada monto: la leyenda completa está en la sección 10, al final de la hoja.
B14: 1. RECURSO HUMANO (valorizado a precio de mercado; no es desembolso)
B15: Rol | C15: Responsable | D15: Horas | E15: Valor hora (CLP) | F15: Costo (CLP) | G15: Observación | H15: Estado
B16: Jefe de Proyecto (JP) | C16: Vicente Rivera | D16: 65 | E16: 13388 | F16: =D16*E16 | G16: Costo empresa $2.142.000 / 160 h. Gestión, control y coordinación. | H16: Valorizado
B17: Arquitecto de Software (ASW) | C17: Vicente Rivera | D17: 65 | E17: 11156 | F17: =D17*E17 | G17: Costo empresa $1.785.000 / 160 h. Arquitectura y despliegue. | H17: Valorizado
B18: Administrador de BBDD (DBA) | C18: Vicente Rivera | D18: 60 | E18: 10041 | F18: =D18*E18 | G18: Costo empresa $1.606.500 / 160 h. PostgreSQL, RLS y scripts. | H18: Valorizado
B19: Programador Full Stack 1 – Backend (PFS 1) | C19: Vicente Rivera | D19: 160 | E19: 7438 | F19: =D19*E19 | G19: Costo empresa $1.190.000 / 160 h. FastAPI, pagos y correos. | H19: Valorizado
B20: Analista de Procesos (AP) | C20: Ignacio Fuenzalida | D20: 90 | E20: 5950 | F20: =D20*E20 | G20: Costo empresa $952.000 / 160 h. ERS, mockups y pruebas. | H20: Valorizado
B21: Programador Full Stack 2 – Frontend (PFS 2) | C21: Ignacio Fuenzalida | D21: 260 | E21: 9669 | F21: =D21*E21 | G21: Costo empresa $1.547.000 / 160 h. Vue.js + Vite. | H21: Valorizado
B22: Subtotal recurso humano | D22: =SUM(D16:D21) | F22: =SUM(F16:F21) | G22: Valor hora tomado de la tabla de roles del Acta (talent.com).
B23: Control de horas: Vicente Rivera | C23: Asignadas / disponibles | D23: =SUMIF($C$16:$C$21,"Vicente Rivera",$D$16:$D$21) | E23: =$C$8*$C$9 | F23: =IF(D23<=E23,"OK","Excede") | G23: Las horas asignadas no deben superar las disponibles.
B24: Control de horas: Ignacio Fuenzalida | C24: Asignadas / disponibles | D24: =SUMIF($C$16:$C$21,"Ignacio Fuenzalida",$D$16:$D$21) | E24: =$C$8*$C$9 | F24: =IF(D24<=E24,"OK","Excede") | G24: Las horas asignadas no deben superar las disponibles.
B26: 2. INFRAESTRUCTURA Y SERVICIOS – OPCIÓN B (PRODUCCIÓN CON REDUNDANCIA)
B27: Servicio | C27: Uso en CuTuCo | D27: Cantidad | E27: Valor unit. (USD) | F27: Costo (CLP) | G27: Observación | H27: Estado
B28: Dominio web (.cl / .com) | C28: Acceso público | D28: 1 | E28: 15 | F28: =D28*E28*$C$6 | G28: Cantidad en años. Estimación de mercado. | H28: Estimado
B29: Vercel Pro | C29: Frontend Vue.js + Vite | D29: 3 | E29: 20 | F29: =D29*E29*$C$6 | G29: Cantidad en meses. USD 20 por usuario al mes. | H29: Estimado
B30: Supabase Pro | C30: PostgreSQL, Auth, PostgREST, Storage | D30: 3 | E30: 25 | F30: =D30*E30*$C$6 | G30: Cantidad en meses. Incluye respaldos diarios. | H30: Estimado
B31: GCP Cloud Run (2 regiones) + Secret Manager | C31: FastAPI + Docker con redundancia | D31: 3 | E31: 40 | F31: =D31*E31*$C$6 | G31: Cantidad en meses. Cerca de 40% más que la Opción A (informe). | H31: Estimado
B32: Resend Pro | C32: Correos de Auth (SMTP) y de negocio (API) | D32: 3 | E32: 20 | F32: =D32*E32*$C$6 | G32: Cantidad en meses. Mayor volumen de correos. | H32: Estimado
B33: Transbank Webpay Mall (producción) | C33: Pagos reales | D33: 3 | E33: 0 | F33: =D33*E33*$C$6 | G33: Sin costo fijo; comisiones por transacción variables y no incluidas. | H33: Confirmado
B34: GitHub Team | C34: Repositorio y CI/CD (2 usuarios) | D34: 3 | E34: 8 | F34: =D34*E34*$C$6 | G34: Cantidad en meses. USD 4 por usuario al mes. | H34: Estimado
B35: Subtotal infraestructura (desembolso) | F35: =SUM(F28:F34) | G35: Costo mensual aproximado de USD 113, dentro del rango USD 100 a 120 del informe.
B37: 3. OTROS COSTOS DEL PROYECTO
B38: Concepto | C38: Detalle | D38: Cantidad | E38: Valor unit. (CLP) | F38: Costo (CLP) | G38: Observación | H38: Estado
B39: Internet y electricidad (trabajo remoto) | C39: Persona-mes | D39: =2*$C$7 | E39: 35000 | F39: =D39*E39 | G39: Supuesto: $35.000 mensuales por integrante. | H39: Estimado
B40: Depreciación de notebooks propios | C40: Equipo-mes | D40: =2*$C$7 | E40: =ROUND($C$11/$C$12,0) | F40: =D40*E40 | G40: Valor del equipo / vida útil. No se compran equipos nuevos. | H40: Estimado
B41: Impresión y material de la presentación final | C41: Global | D41: 1 | E41: 60000 | F41: =D41*E41 | G41: Supuesto del equipo. | H41: Estimado
B42: Herramientas de desarrollo y diseño | C42: Figma Professional (2 licencias) | D42: 6 | E42: 14250 | F42: =D42*E42 | G42: Cantidad en licencias-mes. USD 15 por licencia (a $950). | H42: Estimado
B43: Asesoría legal | C43: Términos, privacidad, Transbank | D43: 1 | E43: 250000 | F43: =D43*E43 | G43: Revisión única; necesaria para cobrar a clientes reales. | H43: Estimado
B44: Revisión de seguridad externa | C44: Pruebas de seguridad | D44: 1 | E44: 400000 | F44: =D44*E44 | G44: Revisa RLS, pagos y manejo de datos bancarios del productor. | H44: Estimado
B45: Subtotal otros costos (desembolso) | F45: =SUM(F39:F44)
B47: 4. RESUMEN DEL PRESUPUESTO ESTIMADO
B48: Concepto | F48: Monto (CLP) | G48: Observación
B49: Desembolso en efectivo (infraestructura + otros costos) | F49: =F35+F45+F72 | G49: Dinero que realmente se paga. Incluye los trámites de la sección 6, hoy registrados en $0 por falta de cotización.
B50: Recurso humano valorizado | F50: =F22 | G50: Referencia de mercado; el equipo no recibe pago.
B51: Subtotal del proyecto | F51: =F49+F50
B52: Contingencia | F52: =F51*$C$10 | G52: Porcentaje definido en los supuestos.
B53: TOTAL PRESUPUESTO ESTIMADO | F53: =F51+F52 | G53: Valor total del proyecto.
B54: Total presupuesto estimado en USD | F54: =F53/$C$6 | G54: Según el tipo de cambio supuesto.
B55: Desembolso en efectivo con contingencia | F55: =F49*(1+$C$10) | G55: Monto mínimo a tener disponible.
B57: 5. PROYECCIÓN ANUAL DE CONTINUIDAD (OPCIÓN B) – REFERENCIAL, NO INCLUIDA EN EL TOTAL
B58: Escenario | C58: Detalle | D58: Meses | E58: Valor mensual (USD) | F58: Costo (CLP) | G58: Observación
B59: Mínimo mensual | C59: Infraestructura productiva | D59: 1 | E59: 100 | F59: =D59*E59*$C$6 | G59: Rango del informe: USD 100 a 120 al mes.
B60: Máximo mensual | C60: Infraestructura productiva | D60: 1 | E60: 120 | F60: =D60*E60*$C$6 | G60: Rango del informe: USD 100 a 120 al mes.
B61: Mínimo anual | C61: Primer año en producción | D61: 12 | E61: 100 | F61: =D61*E61*$C$6 | G61: Proyección de continuidad.
B62: Máximo anual | C62: Primer año en producción | D62: 12 | E62: 120 | F62: =D62*E62*$C$6 | G62: Más comisiones Webpay por transacción (variables, no incluidas).
B65: 6. TRÁMITES DE CONSTITUCIÓN, SII Y PATENTE MUNICIPAL – UN REGISTRO POR CONCEPTO (MONTOS NO COTIZADOS)
B66: Concepto | C66: Naturaleza | D66: Cantidad | E66: Valor unit. (CLP) | F66: Costo (CLP) | G66: Observación | H66: Estado
B67: Constitución de la empresa (EIRL o SpA) y firma ante notario | C67: Trámite legal y notarial | D67: 1 | E67: 0 | F67: =D67*E67 | G67: Registro único del concepto: no se repite en otras filas de esta planilla ni en el Plan de Calidad y de Costos. Sin monto cotizado: se deja en $0 y el total se recalcula al ingresar el valor unitario. | H67: Pendiente de cotización
B68: Inscripción en el Registro de Empresas y Sociedades | C68: Trámite legal | D68: 1 | E68: 0 | F68: =D68*E68 | G68: Supuesto a validar: la inscripción en línea no tendría costo directo para el usuario. Confirmar en el sitio del Registro de Empresas y Sociedades antes de usarlo como referencia. | H68: Pendiente de confirmación
B69: Inicio de actividades ante el SII | C69: Trámite tributario | D69: 1 | E69: 0 | F69: =D69*E69 | G69: Se realiza en línea en el sitio del SII y es requisito para emitir documentos tributarios. Supuesto a validar: no tendría costo directo; si se requiere firma electrónica avanzada, su valor debe cotizarse aparte. | H69: Pendiente de confirmación
B70: Patente municipal (permiso de funcionamiento) | C70: Trámite municipal | D70: 1 | E70: 0 | F70: =D70*E70 | G70: El valor depende de la comuna y del capital declarado. Debe cotizarse en la municipalidad del domicilio comercial. | H70: Pendiente de cotización
B71: Habilitación de facturación y boleta electrónica del SII | C71: Trámite tributario | D71: 1 | E71: 0 | F71: =D71*E71 | G71: Supuesto a validar: el SII ofrece un sistema de facturación electrónica sin costo para el contribuyente. Confirmar antes de darlo por gratuito. No duplica el inicio de actividades. | H71: Pendiente de confirmación
B72: Subtotal trámites (registrado en $0 hasta contar con cotización) | F72: =SUM(F67:F71) | G72: No altera el total estimado mientras no exista un monto cotizado. Al reemplazar los valores unitarios, el desembolso en efectivo (sección 4) se recalcula solo.
B74: 7. RESOLUCIÓN SANITARIA Y ALCANCE DE PRODUCTOS (CONDICIÓN POR VALIDAR CON LA AUTORIDAD SANITARIA)
B75: Alternativa | C75: Alcance de la oferta | D75: Cantidad | E75: Valor unit. (CLP) | F75: Costo (CLP) | G75: Observación | H75: Estado
B76: Alternativa A: oferta limitada a productos sin procesar (recomendada para el MVP) | C76: Frutas, verduras y huevos sin procesar, sin elaboración ni envasado propio | D76: 1 | E76: 0 | F76: =D76*E76 | G76: Efecto analizado: reduce la exposición a exigencias sanitarias de elaboración y etiquetado, pero la necesidad de resolución sanitaria sigue siendo una condición por validar con la SEREMI de Salud, porque depende del tipo de producto, del lugar de acopio y del transporte. No se afirma que sea exigible ni que deje de serlo. | H76: Pendiente de confirmación
B77: Alternativa B: oferta con productos procesados o envasados (no adoptada) | C77: Productos elaborados, envasados o con etiquetado propio | D77: 1 | E77: 0 | F77: =D77*E77 | G77: Aumenta la exposición a exigencias sanitarias del elaborador o de la bodega y a requisitos de etiquetado, con posible inversión y plazos adicionales. | H77: Pendiente de cotización
B78: Etiquetado y transporte de alimentos | C78: Información del producto y condiciones del traslado | D78: 1 | E78: 0 | F78: =D78*E78 | G78: Condición por validar con la autoridad sanitaria y con los requisitos aplicables. No se declara como obligación vigente del MVP ni como gasto comprometido. | H78: Pendiente de confirmación
B79: Subtotal resolución sanitaria y etiquetado (sin cotización) | F79: =SUM(F76:F78) | G79: Se mantiene en $0: no hay cotización ni pronunciamiento de la autoridad sanitaria.
B81: 8. DELIVERY: ALTERNATIVAS EVALUADAS (COSTOS, INGRESOS Y RIESGOS)
B82: Alternativa | C82: Descripción | D82: Cantidad | E82: Valor unit. (CLP) | F82: Costo (CLP) | G82: Observación | H82: Estado
B83: 1. Despacho a cargo del productor (ADOPTADA: línea base del MVP) | C83: El Vendedor entrega el pedido y lo cierra con el código de verificación (RF-007 y RF-025) | D83: 1 | E83: 0 | F83: =D83*E83 | G83: Adoptada porque es la definida en el ERS: no exige inversión ni contratación de terceros y su costo para CuTuCo es $0. En ingresos, la tarifa fija de $3.500 por pedido se descuenta en el Split Payment (RF-014); la contraprestación asociada a esa tarifa está pendiente de confirmación. Riesgo: la entrega depende de la capacidad de cada productor y CuTuCo no tiene respaldo logístico propio. | H83: Confirmado
B84: 2. Reparto externalizado (evaluada, no contratada) | C84: Empresa de reparto o red de repartidores externos con tarifa por entrega | D84: 1 | E84: 0 | F84: =D84*E84 | G84: Sin inversión en flota, con costo variable por pedido y dependencia de terceros. Exige definir si la tarifa fija de $3.500 cubre la entrega. No se contrata durante el MVP. | H84: Pendiente de cotización
B85: 3. Flota y repartidores propios (evaluada, no contratada) | C85: Camiones, furgones o motos propios y repartidores contratados | D85: 1 | E85: 0 | F85: =D85*E85 | G85: Entrega controlada, con inversión inicial y costo fijo mensual (vehículos, combustible, seguros y remuneraciones). No se contrata: depende del volumen real de pedidos y de una decisión formal de inversión. | H85: Pendiente de cotización
B86: Subtotal delivery (alternativas no contratadas, sin cotización) | F86: =SUM(F83:F85) | G86: Criterio de decisión: se adopta la alternativa 1 por ser la línea base del MVP y no generar desembolso. Las alternativas 2 y 3 se reevalúan solo si el volumen de pedidos lo justifica, con cotización y presupuesto aprobado.
B88: 9. CONDICIONES TRIBUTARIAS, COMERCIALES, SANITARIAS Y OPERATIVAS A VALIDAR
B89: Tema | C89: Qué se debe validar y efecto en el presupuesto | G89: Nota | H89: Estado
B90: IVA y boleta electrónica | C90: El ERS define boleta a consumidor final con RUT genérico 66.666.666-6 y factura cuando el comprador es una empresa (B2B). Falta confirmar el tratamiento del IVA sobre la comisión y sobre la tarifa fija por pedido, y si los montos del fee se expresan con o sin IVA. Efecto en el presupuesto: por definir. | G90: Requiere revisión de un contador; pendiente de confirmación. | H90: Pendiente de confirmación
B91: Patente municipal | C91: Aplicabilidad, comuna y base de cálculo del permiso de funcionamiento. Efecto: costo periódico no incluido en el total hasta contar con cotización. | G91: Registrada en la sección 6. | H91: Pendiente de cotización
B92: Resolución sanitaria | C92: Aplicabilidad según el tipo de producto, el lugar de acopio y el transporte. Efecto: podría exigir habilitación de bodega o de sala de proceso, hoy no presupuestada. | G92: Analizada en la sección 7. | H92: Pendiente de confirmación
B93: Etiquetado de productos | C93: Información obligatoria del producto cuando corresponda (origen, peso, fecha y responsable). Efecto: diseño e impresión de etiquetas, hoy no presupuestados. | G93: Condición por validar con la autoridad sanitaria. | H93: Pendiente de confirmación
B94: Transporte de alimentos | C94: Condiciones del traslado (temperatura, envases y limpieza) cuando el despacho lo realiza el productor. Efecto: podría exigir envases o cajas adicionales. | G94: Condición por validar. | H94: Pendiente de confirmación
B95: Comisión de Transbank por transacción | C95: Monto de la comisión y quién la asume en el contrato de Webpay Mall. Efecto: si la asume CuTuCo, se descuenta del ingreso por fee y cambia el punto de equilibrio. | G95: No incluida en el total; pendiente de confirmación. | H95: Pendiente de confirmación
B96: Registro del Código de Comercio Mall | C96: El código se obtiene en el trámite con Transbank y es un paso posterior e independiente de la aprobación de la postulación. Mientras un productor no lo tenga, no puede operar y sus productos no se muestran en el catálogo. | G96: Trámite fuera del flujo principal de la plataforma. | H96: Pendiente de confirmación
B97: Datos bancarios y documentos de postulación | C97: Protección mediante RLS, policies, grants y permisos de almacenamiento de Supabase. Efecto: sin costo adicional durante el MVP. | G97: La inscripción de la cuenta bancaria en Transbank es un trámite externo al flujo de la plataforma; los datos recibidos se protegen con RLS, policies, grants y permisos de almacenamiento. | H97: Confirmado
B98: Suscripción mensual por productor | C98: Precio y adopción del modelo proyectado. Efecto en los ingresos: se modela desde el Año 1 como negocio proyectado. | G98: La facturación de la suscripción no forma parte del MVP. | H98: Fuera del MVP
B99: Delivery | C99: Alternativa adoptada y su efecto en costos, ingresos y riesgos. | G99: Analizada en la sección 8. | H99: Confirmado
B101: 10. ESTADOS DEL PRESUPUESTO Y LEYENDA (APLICA A TODAS LAS FILAS DE ESTA HOJA)
B102: Estado | C102: Significado
B103: Confirmado | C103: Monto o condición verificada en la documentación del proyecto o del proveedor. Incluye los niveles gratuitos, que hoy no generan desembolso.
B104: Estimado | C104: Referencia del equipo para el mercado chileno, sin cotización formal. Puede cambiar al momento de contratar.
B105: Valorizado | C105: Costo de referencia del trabajo del equipo a precio de mercado. No genera desembolso.
B106: Pendiente de cotización | C106: No hay monto sustentable: se registra en $0 y se incorporará al total cuando exista una cotización o un valor oficial.
B107: Pendiente de confirmación | C107: Falta validar la exigibilidad, la aplicabilidad o la cifra antes de comprometer un gasto.
B108: Fuera del MVP | C108: Concepto identificado y modelado como negocio proyectado, pero no activo en esta versión.

Sheet Medio Presupuesto
B1: PRESUPUESTO ESTIMADO – ESCENARIO MEDIO – PLAN DE COSTOS
B2: CuTuCo (Cultiva Tu Compra) – Marketplace SaaS B2B2C | Duoc UC Plaza Norte – Ingeniería en Informática
B3: Duración: 13 semanas (11/09/2026 – 10/12/2026) | Equipo: Vicente Rivera e Ignacio Fuenzalida | Moneda: pesos chilenos (CLP)
B4: Opción A reforzada: planes pagados en Supabase, Vercel y Cloud Run (sin depender de créditos), más horas de QA y asesoría legal básica.
B5: SUPUESTOS (celdas azules con fondo amarillo = editables)
B6: Tipo de cambio (CLP por USD) | C6: 950 | D6: Supuesto del equipo; ajustar al valor del día de pago.
B7: Duración del proyecto (meses) | C7: 3 | D7: 13 semanas ≈ 3 meses.
B8: Semanas de trabajo | C8: 13 | D8: Acta de Constitución: semanas 1 a 13.
B9: Horas por semana por integrante | C9: 24 | D9: Dedicación estimada compatible con la carga académica.
B10: Contingencia sobre el subtotal | C10: 0.15 | D10: Mayor reserva por servicios pagados y más horas de pruebas.
B11: Valor de un notebook propio (CLP) | C11: 800000 | D11: Estimación de mercado Chile.
B12: Vida útil del notebook (meses) | C12: 36 | D12: Depreciación lineal.
B13: Estado de cada monto: la leyenda completa está en la sección 10, al final de la hoja.
B14: 1. RECURSO HUMANO (valorizado a precio de mercado; no es desembolso)
B15: Rol | C15: Responsable | D15: Horas | E15: Valor hora (CLP) | F15: Costo (CLP) | G15: Observación | H15: Estado
B16: Jefe de Proyecto (JP) | C16: Vicente Rivera | D16: 55 | E16: 13388 | F16: =D16*E16 | G16: Costo empresa $2.142.000 / 160 h. Gestión, control y coordinación. | H16: Valorizado
B17: Arquitecto de Software (ASW) | C17: Vicente Rivera | D17: 55 | E17: 11156 | F17: =D17*E17 | G17: Costo empresa $1.785.000 / 160 h. Arquitectura y despliegue. | H17: Valorizado
B18: Administrador de BBDD (DBA) | C18: Vicente Rivera | D18: 55 | E18: 10041 | F18: =D18*E18 | G18: Costo empresa $1.606.500 / 160 h. PostgreSQL, RLS y scripts. | H18: Valorizado
B19: Programador Full Stack 1 – Backend (PFS 1) | C19: Vicente Rivera | D19: 135 | E19: 7438 | F19: =D19*E19 | G19: Costo empresa $1.190.000 / 160 h. FastAPI, pagos y correos. | H19: Valorizado
B20: Analista de Procesos (AP) | C20: Ignacio Fuenzalida | D20: 70 | E20: 5950 | F20: =D20*E20 | G20: Costo empresa $952.000 / 160 h. ERS, mockups y pruebas. | H20: Valorizado
B21: Programador Full Stack 2 – Frontend (PFS 2) | C21: Ignacio Fuenzalida | D21: 230 | E21: 9669 | F21: =D21*E21 | G21: Costo empresa $1.547.000 / 160 h. Vue.js + Vite. | H21: Valorizado
B22: Subtotal recurso humano | D22: =SUM(D16:D21) | F22: =SUM(F16:F21) | G22: Valor hora tomado de la tabla de roles del Acta (talent.com).
B23: Control de horas: Vicente Rivera | C23: Asignadas / disponibles | D23: =SUMIF($C$16:$C$21,"Vicente Rivera",$D$16:$D$21) | E23: =$C$8*$C$9 | F23: =IF(D23<=E23,"OK","Excede") | G23: Las horas asignadas no deben superar las disponibles.
B24: Control de horas: Ignacio Fuenzalida | C24: Asignadas / disponibles | D24: =SUMIF($C$16:$C$21,"Ignacio Fuenzalida",$D$16:$D$21) | E24: =$C$8*$C$9 | F24: =IF(D24<=E24,"OK","Excede") | G24: Las horas asignadas no deben superar las disponibles.
B26: 2. INFRAESTRUCTURA Y SERVICIOS – OPCIÓN A CON PLANES PAGADOS
B27: Servicio | C27: Uso en CuTuCo | D27: Cantidad | E27: Valor unit. (USD) | F27: Costo (CLP) | G27: Observación | H27: Estado
B28: Dominio web (.cl / .com) | C28: Acceso público | D28: 1 | E28: 15 | F28: =D28*E28*$C$6 | G28: Cantidad en años. Estimación de mercado. | H28: Estimado
B29: Vercel Pro | C29: Frontend Vue.js + Vite | D29: 3 | E29: 20 | F29: =D29*E29*$C$6 | G29: Cantidad en meses. USD 20 por usuario al mes (1 usuario). | H29: Estimado
B30: Supabase Pro | C30: PostgreSQL, Auth, PostgREST, Storage | D30: 3 | E30: 25 | F30: =D30*E30*$C$6 | G30: Cantidad en meses. Incluye respaldos diarios. | H30: Estimado
B31: GCP Cloud Run + Secret Manager | C31: FastAPI + Docker (us-central1) | D31: 3 | E31: 15 | F31: =D31*E31*$C$6 | G31: Cantidad en meses. Consumo estimado sin créditos GCP. | H31: Estimado
B32: Resend | C32: Correos de Auth (SMTP) y de negocio (API) | D32: 3 | E32: 0 | F32: =D32*E32*$C$6 | G32: Cantidad en meses. Nivel gratuito (hasta 3.000 correos/mes). | H32: Confirmado
B33: Transbank Webpay Mall Test | C33: Pagos en ambiente de integración | D33: 3 | E33: 0 | F33: =D33*E33*$C$6 | G33: Ambiente de pruebas sin costo. | H33: Confirmado
B34: GitHub + GitHub Actions | C34: Repositorio y CI/CD | D34: 3 | E34: 0 | F34: =D34*E34*$C$6 | G34: Cantidad en meses. Plan gratuito. | H34: Confirmado
B35: Subtotal infraestructura (desembolso) | F35: =SUM(F28:F34) | G35: Costo mensual aproximado de USD 60 más el dominio.
B37: 3. OTROS COSTOS DEL PROYECTO
B38: Concepto | C38: Detalle | D38: Cantidad | E38: Valor unit. (CLP) | F38: Costo (CLP) | G38: Observación | H38: Estado
B39: Internet y electricidad (trabajo remoto) | C39: Persona-mes | D39: =2*$C$7 | E39: 30000 | F39: =D39*E39 | G39: Supuesto: $30.000 mensuales por integrante. | H39: Estimado
B40: Depreciación de notebooks propios | C40: Equipo-mes | D40: =2*$C$7 | E40: =ROUND($C$11/$C$12,0) | F40: =D40*E40 | G40: Valor del equipo / vida útil. No se compran equipos nuevos. | H40: Estimado
B41: Impresión y material de la presentación final | C41: Global | D41: 1 | E41: 40000 | F41: =D41*E41 | G41: Supuesto del equipo. | H41: Estimado
B42: Herramientas de desarrollo y diseño | C42: Figma Professional (2 licencias) | D42: 6 | E42: 14250 | F42: =D42*E42 | G42: Cantidad en licencias-mes. USD 15 por licencia (a $950). | H42: Estimado
B43: Asesoría legal básica | C43: Términos y condiciones, privacidad | D43: 1 | E43: 150000 | F43: =D43*E43 | G43: Revisión única; marketplace con datos personales y bancarios. | H43: Estimado
B44: Subtotal otros costos (desembolso) | F44: =SUM(F39:F43)
B46: 4. RESUMEN DEL PRESUPUESTO ESTIMADO
B47: Concepto | F47: Monto (CLP) | G47: Observación
B48: Desembolso en efectivo (infraestructura + otros costos) | F48: =F35+F44+F71 | G48: Dinero que realmente se paga. Incluye los trámites de la sección 6, hoy registrados en $0 por falta de cotización.
B49: Recurso humano valorizado | F49: =F22 | G49: Referencia de mercado; el equipo no recibe pago.
B50: Subtotal del proyecto | F50: =F48+F49
B51: Contingencia | F51: =F50*$C$10 | G51: Porcentaje definido en los supuestos.
B52: TOTAL PRESUPUESTO ESTIMADO | F52: =F50+F51 | G52: Valor total del proyecto.
B53: Total presupuesto estimado en USD | F53: =F52/$C$6 | G53: Según el tipo de cambio supuesto.
B54: Desembolso en efectivo con contingencia | F54: =F48*(1+$C$10) | G54: Monto mínimo a tener disponible.
B56: 5. PROYECCIÓN ANUAL DE CONTINUIDAD (OPCIÓN B) – REFERENCIAL, NO INCLUIDA EN EL TOTAL
B57: Escenario | C57: Detalle | D57: Meses | E57: Valor mensual (USD) | F57: Costo (CLP) | G57: Observación
B58: Mínimo mensual | C58: Infraestructura productiva | D58: 1 | E58: 100 | F58: =D58*E58*$C$6 | G58: Rango del informe: USD 100 a 120 al mes.
B59: Máximo mensual | C59: Infraestructura productiva | D59: 1 | E59: 120 | F59: =D59*E59*$C$6 | G59: Rango del informe: USD 100 a 120 al mes.
B60: Mínimo anual | C60: Primer año en producción | D60: 12 | E60: 100 | F60: =D60*E60*$C$6 | G60: Proyección de continuidad.
B61: Máximo anual | C61: Primer año en producción | D61: 12 | E61: 120 | F61: =D61*E61*$C$6 | G61: Más comisiones Webpay por transacción (variables, no incluidas).
B64: 6. TRÁMITES DE CONSTITUCIÓN, SII Y PATENTE MUNICIPAL – UN REGISTRO POR CONCEPTO (MONTOS NO COTIZADOS)
B65: Concepto | C65: Naturaleza | D65: Cantidad | E65: Valor unit. (CLP) | F65: Costo (CLP) | G65: Observación | H65: Estado
B66: Constitución de la empresa (EIRL o SpA) y firma ante notario | C66: Trámite legal y notarial | D66: 1 | E66: 0 | F66: =D66*E66 | G66: Registro único del concepto: no se repite en otras filas de esta planilla ni en el Plan de Calidad y de Costos. Sin monto cotizado: se deja en $0 y el total se recalcula al ingresar el valor unitario. | H66: Pendiente de cotización
B67: Inscripción en el Registro de Empresas y Sociedades | C67: Trámite legal | D67: 1 | E67: 0 | F67: =D67*E67 | G67: Supuesto a validar: la inscripción en línea no tendría costo directo para el usuario. Confirmar en el sitio del Registro de Empresas y Sociedades antes de usarlo como referencia. | H67: Pendiente de confirmación
B68: Inicio de actividades ante el SII | C68: Trámite tributario | D68: 1 | E68: 0 | F68: =D68*E68 | G68: Se realiza en línea en el sitio del SII y es requisito para emitir documentos tributarios. Supuesto a validar: no tendría costo directo; si se requiere firma electrónica avanzada, su valor debe cotizarse aparte. | H68: Pendiente de confirmación
B69: Patente municipal (permiso de funcionamiento) | C69: Trámite municipal | D69: 1 | E69: 0 | F69: =D69*E69 | G69: El valor depende de la comuna y del capital declarado. Debe cotizarse en la municipalidad del domicilio comercial. | H69: Pendiente de cotización
B70: Habilitación de facturación y boleta electrónica del SII | C70: Trámite tributario | D70: 1 | E70: 0 | F70: =D70*E70 | G70: Supuesto a validar: el SII ofrece un sistema de facturación electrónica sin costo para el contribuyente. Confirmar antes de darlo por gratuito. No duplica el inicio de actividades. | H70: Pendiente de confirmación
B71: Subtotal trámites (registrado en $0 hasta contar con cotización) | F71: =SUM(F66:F70) | G71: No altera el total estimado mientras no exista un monto cotizado. Al reemplazar los valores unitarios, el desembolso en efectivo (sección 4) se recalcula solo.
B73: 7. RESOLUCIÓN SANITARIA Y ALCANCE DE PRODUCTOS (CONDICIÓN POR VALIDAR CON LA AUTORIDAD SANITARIA)
B74: Alternativa | C74: Alcance de la oferta | D74: Cantidad | E74: Valor unit. (CLP) | F74: Costo (CLP) | G74: Observación | H74: Estado
B75: Alternativa A: oferta limitada a productos sin procesar (recomendada para el MVP) | C75: Frutas, verduras y huevos sin procesar, sin elaboración ni envasado propio | D75: 1 | E75: 0 | F75: =D75*E75 | G75: Efecto analizado: reduce la exposición a exigencias sanitarias de elaboración y etiquetado, pero la necesidad de resolución sanitaria sigue siendo una condición por validar con la SEREMI de Salud, porque depende del tipo de producto, del lugar de acopio y del transporte. No se afirma que sea exigible ni que deje de serlo. | H75: Pendiente de confirmación
B76: Alternativa B: oferta con productos procesados o envasados (no adoptada) | C76: Productos elaborados, envasados o con etiquetado propio | D76: 1 | E76: 0 | F76: =D76*E76 | G76: Aumenta la exposición a exigencias sanitarias del elaborador o de la bodega y a requisitos de etiquetado, con posible inversión y plazos adicionales. | H76: Pendiente de cotización
B77: Etiquetado y transporte de alimentos | C77: Información del producto y condiciones del traslado | D77: 1 | E77: 0 | F77: =D77*E77 | G77: Condición por validar con la autoridad sanitaria y con los requisitos aplicables. No se declara como obligación vigente del MVP ni como gasto comprometido. | H77: Pendiente de confirmación
B78: Subtotal resolución sanitaria y etiquetado (sin cotización) | F78: =SUM(F75:F77) | G78: Se mantiene en $0: no hay cotización ni pronunciamiento de la autoridad sanitaria.
B80: 8. DELIVERY: ALTERNATIVAS EVALUADAS (COSTOS, INGRESOS Y RIESGOS)
B81: Alternativa | C81: Descripción | D81: Cantidad | E81: Valor unit. (CLP) | F81: Costo (CLP) | G81: Observación | H81: Estado
B82: 1. Despacho a cargo del productor (ADOPTADA: línea base del MVP) | C82: El Vendedor entrega el pedido y lo cierra con el código de verificación (RF-007 y RF-025) | D82: 1 | E82: 0 | F82: =D82*E82 | G82: Adoptada porque es la definida en el ERS: no exige inversión ni contratación de terceros y su costo para CuTuCo es $0. En ingresos, la tarifa fija de $3.500 por pedido se descuenta en el Split Payment (RF-014); la contraprestación asociada a esa tarifa está pendiente de confirmación. Riesgo: la entrega depende de la capacidad de cada productor y CuTuCo no tiene respaldo logístico propio. | H82: Confirmado
B83: 2. Reparto externalizado (evaluada, no contratada) | C83: Empresa de reparto o red de repartidores externos con tarifa por entrega | D83: 1 | E83: 0 | F83: =D83*E83 | G83: Sin inversión en flota, con costo variable por pedido y dependencia de terceros. Exige definir si la tarifa fija de $3.500 cubre la entrega. No se contrata durante el MVP. | H83: Pendiente de cotización
B84: 3. Flota y repartidores propios (evaluada, no contratada) | C84: Camiones, furgones o motos propios y repartidores contratados | D84: 1 | E84: 0 | F84: =D84*E84 | G84: Entrega controlada, con inversión inicial y costo fijo mensual (vehículos, combustible, seguros y remuneraciones). No se contrata: depende del volumen real de pedidos y de una decisión formal de inversión. | H84: Pendiente de cotización
B85: Subtotal delivery (alternativas no contratadas, sin cotización) | F85: =SUM(F82:F84) | G85: Criterio de decisión: se adopta la alternativa 1 por ser la línea base del MVP y no generar desembolso. Las alternativas 2 y 3 se reevalúan solo si el volumen de pedidos lo justifica, con cotización y presupuesto aprobado.
B87: 9. CONDICIONES TRIBUTARIAS, COMERCIALES, SANITARIAS Y OPERATIVAS A VALIDAR
B88: Tema | C88: Qué se debe validar y efecto en el presupuesto | G88: Nota | H88: Estado
B89: IVA y boleta electrónica | C89: El ERS define boleta a consumidor final con RUT genérico 66.666.666-6 y factura cuando el comprador es una empresa (B2B). Falta confirmar el tratamiento del IVA sobre la comisión y sobre la tarifa fija por pedido, y si los montos del fee se expresan con o sin IVA. Efecto en el presupuesto: por definir. | G89: Requiere revisión de un contador; pendiente de confirmación. | H89: Pendiente de confirmación
B90: Patente municipal | C90: Aplicabilidad, comuna y base de cálculo del permiso de funcionamiento. Efecto: costo periódico no incluido en el total hasta contar con cotización. | G90: Registrada en la sección 6. | H90: Pendiente de cotización
B91: Resolución sanitaria | C91: Aplicabilidad según el tipo de producto, el lugar de acopio y el transporte. Efecto: podría exigir habilitación de bodega o de sala de proceso, hoy no presupuestada. | G91: Analizada en la sección 7. | H91: Pendiente de confirmación
B92: Etiquetado de productos | C92: Información obligatoria del producto cuando corresponda (origen, peso, fecha y responsable). Efecto: diseño e impresión de etiquetas, hoy no presupuestados. | G92: Condición por validar con la autoridad sanitaria. | H92: Pendiente de confirmación
B93: Transporte de alimentos | C93: Condiciones del traslado (temperatura, envases y limpieza) cuando el despacho lo realiza el productor. Efecto: podría exigir envases o cajas adicionales. | G93: Condición por validar. | H93: Pendiente de confirmación
B94: Comisión de Transbank por transacción | C94: Monto de la comisión y quién la asume en el contrato de Webpay Mall. Efecto: si la asume CuTuCo, se descuenta del ingreso por fee y cambia el punto de equilibrio. | G94: No incluida en el total; pendiente de confirmación. | H94: Pendiente de confirmación
B95: Registro del Código de Comercio Mall | C95: El código se obtiene en el trámite con Transbank y es un paso posterior e independiente de la aprobación de la postulación. Mientras un productor no lo tenga, no puede operar y sus productos no se muestran en el catálogo. | G95: Trámite fuera del flujo principal de la plataforma. | H95: Pendiente de confirmación
B96: Datos bancarios y documentos de postulación | C96: Protección mediante RLS, policies, grants y permisos de almacenamiento de Supabase. Efecto: sin costo adicional durante el MVP. | G96: La inscripción de la cuenta bancaria en Transbank es un trámite externo al flujo de la plataforma; los datos recibidos se protegen con RLS, policies, grants y permisos de almacenamiento. | H96: Confirmado
B97: Suscripción mensual por productor | C97: Precio y adopción del modelo proyectado. Efecto en los ingresos: se modela desde el Año 1 como negocio proyectado. | G97: La facturación de la suscripción no forma parte del MVP. | H97: Fuera del MVP
B98: Delivery | C98: Alternativa adoptada y su efecto en costos, ingresos y riesgos. | G98: Analizada en la sección 8. | H98: Confirmado
B100: 10. ESTADOS DEL PRESUPUESTO Y LEYENDA (APLICA A TODAS LAS FILAS DE ESTA HOJA)
B101: Estado | C101: Significado
B102: Confirmado | C102: Monto o condición verificada en la documentación del proyecto o del proveedor. Incluye los niveles gratuitos, que hoy no generan desembolso.
B103: Estimado | C103: Referencia del equipo para el mercado chileno, sin cotización formal. Puede cambiar al momento de contratar.
B104: Valorizado | C104: Costo de referencia del trabajo del equipo a precio de mercado. No genera desembolso.
B105: Pendiente de cotización | C105: No hay monto sustentable: se registra en $0 y se incorporará al total cuando exista una cotización o un valor oficial.
B106: Pendiente de confirmación | C106: Falta validar la exigibilidad, la aplicabilidad o la cifra antes de comprometer un gasto.
B107: Fuera del MVP | C107: Concepto identificado y modelado como negocio proyectado, pero no activo en esta versión.

Sheet Bajo Presupuesto
B1: PRESUPUESTO ESTIMADO – ESCENARIO BAJO – PLAN DE COSTOS
B2: CuTuCo (Cultiva Tu Compra) – Marketplace SaaS B2B2C | Duoc UC Plaza Norte – Ingeniería en Informática
B3: Duración: 13 semanas (11/09/2026 – 10/12/2026) | Equipo: Vicente Rivera e Ignacio Fuenzalida | Moneda: pesos chilenos (CLP)
B4: Opción A: MVP académico con niveles gratuitos y créditos GCP. Equipo de dos personas, alcance de 22 requerimientos, sin gasto productivo.
B5: SUPUESTOS (celdas azules con fondo amarillo = editables)
B6: Tipo de cambio (CLP por USD) | C6: 950 | D6: Supuesto del equipo; ajustar al valor del día de pago.
B7: Duración del proyecto (meses) | C7: 3 | D7: 13 semanas ≈ 3 meses.
B8: Semanas de trabajo | C8: 13 | D8: Acta de Constitución: semanas 1 a 13.
B9: Horas por semana por integrante | C9: 20 | D9: Dedicación estimada compatible con la carga académica.
B10: Contingencia sobre el subtotal | C10: 0.1 | D10: Reserva básica; la infraestructura es casi gratuita.
B11: Valor de un notebook propio (CLP) | C11: 700000 | D11: Estimación de mercado Chile.
B12: Vida útil del notebook (meses) | C12: 36 | D12: Depreciación lineal.
B13: Estado de cada monto: la leyenda completa está en la sección 10, al final de la hoja.
B14: 1. RECURSO HUMANO (valorizado a precio de mercado; no es desembolso)
B15: Rol | C15: Responsable | D15: Horas | E15: Valor hora (CLP) | F15: Costo (CLP) | G15: Observación | H15: Estado
B16: Jefe de Proyecto (JP) | C16: Vicente Rivera | D16: 50 | E16: 13388 | F16: =D16*E16 | G16: Costo empresa $2.142.000 / 160 h. Gestión, control y coordinación. | H16: Valorizado
B17: Arquitecto de Software (ASW) | C17: Vicente Rivera | D17: 45 | E17: 11156 | F17: =D17*E17 | G17: Costo empresa $1.785.000 / 160 h. Arquitectura y despliegue. | H17: Valorizado
B18: Administrador de BBDD (DBA) | C18: Vicente Rivera | D18: 45 | E18: 10041 | F18: =D18*E18 | G18: Costo empresa $1.606.500 / 160 h. PostgreSQL, RLS y scripts. | H18: Valorizado
B19: Programador Full Stack 1 – Backend (PFS 1) | C19: Vicente Rivera | D19: 120 | E19: 7438 | F19: =D19*E19 | G19: Costo empresa $1.190.000 / 160 h. FastAPI, pagos y correos. | H19: Valorizado
B20: Analista de Procesos (AP) | C20: Ignacio Fuenzalida | D20: 60 | E20: 5950 | F20: =D20*E20 | G20: Costo empresa $952.000 / 160 h. ERS, mockups y pruebas. | H20: Valorizado
B21: Programador Full Stack 2 – Frontend (PFS 2) | C21: Ignacio Fuenzalida | D21: 200 | E21: 9669 | F21: =D21*E21 | G21: Costo empresa $1.547.000 / 160 h. Vue.js + Vite. | H21: Valorizado
B22: Subtotal recurso humano | D22: =SUM(D16:D21) | F22: =SUM(F16:F21) | G22: Valor hora tomado de la tabla de roles del Acta (talent.com).
B23: Control de horas: Vicente Rivera | C23: Asignadas / disponibles | D23: =SUMIF($C$16:$C$21,"Vicente Rivera",$D$16:$D$21) | E23: =$C$8*$C$9 | F23: =IF(D23<=E23,"OK","Excede") | G23: Las horas asignadas no deben superar las disponibles.
B24: Control de horas: Ignacio Fuenzalida | C24: Asignadas / disponibles | D24: =SUMIF($C$16:$C$21,"Ignacio Fuenzalida",$D$16:$D$21) | E24: =$C$8*$C$9 | F24: =IF(D24<=E24,"OK","Excede") | G24: Las horas asignadas no deben superar las disponibles.
B26: 2. INFRAESTRUCTURA Y SERVICIOS – OPCIÓN A (MVP ACADÉMICO)
B27: Servicio | C27: Uso en CuTuCo | D27: Cantidad | E27: Valor unit. (USD) | F27: Costo (CLP) | G27: Observación | H27: Estado
B28: Dominio web | C28: Acceso público | D28: 1 | E28: 12 | F28: =D28*E28*$C$6 | G28: Cantidad en años. Costo del informe: USD 12 al año. | H28: Estimado
B29: Vercel Hobby | C29: Frontend Vue.js + Vite | D29: 3 | E29: 0 | F29: =D29*E29*$C$6 | G29: Cantidad en meses. Nivel gratuito. | H29: Confirmado
B30: Supabase (nivel gratuito) | C30: PostgreSQL, Auth, PostgREST, Storage | D30: 3 | E30: 0 | F30: =D30*E30*$C$6 | G30: Cantidad en meses. Nivel gratuito. | H30: Confirmado
B31: GCP Cloud Run + Secret Manager | C31: FastAPI + Docker (us-central1) | D31: 3 | E31: 0 | F31: =D31*E31*$C$6 | G31: Cubierto por créditos GCP de USD 300 (vigentes hasta el 29/11). | H31: Confirmado
B32: Resend | C32: Correos de Auth (SMTP) y de negocio (API) | D32: 3 | E32: 0 | F32: =D32*E32*$C$6 | G32: Cantidad en meses. Nivel gratuito. | H32: Confirmado
B33: Transbank Webpay Mall Test | C33: Pagos en ambiente de integración | D33: 3 | E33: 0 | F33: =D33*E33*$C$6 | G33: Ambiente de pruebas sin costo. | H33: Confirmado
B34: GitHub + GitHub Actions | C34: Repositorio y CI/CD | D34: 3 | E34: 0 | F34: =D34*E34*$C$6 | G34: Cantidad en meses. Plan gratuito. | H34: Confirmado
B35: Subtotal infraestructura (desembolso) | F35: =SUM(F28:F34) | G35: Coincide con el orden de USD 12 indicado en el Acta.
B37: 3. OTROS COSTOS DEL PROYECTO
B38: Concepto | C38: Detalle | D38: Cantidad | E38: Valor unit. (CLP) | F38: Costo (CLP) | G38: Observación | H38: Estado
B39: Internet y electricidad (trabajo remoto) | C39: Persona-mes | D39: =2*$C$7 | E39: 25000 | F39: =D39*E39 | G39: Supuesto: $25.000 mensuales por integrante. | H39: Estimado
B40: Depreciación de notebooks propios | C40: Equipo-mes | D40: =2*$C$7 | E40: =ROUND($C$11/$C$12,0) | F40: =D40*E40 | G40: Valor del equipo / vida útil. No se compran equipos nuevos. | H40: Estimado
B41: Impresión y material de la presentación final | C41: Global | D41: 1 | E41: 30000 | F41: =D41*E41 | G41: Supuesto del equipo. | H41: Estimado
B42: Herramientas de desarrollo y diseño | C42: VS Code, DBeaver, Figma y GitHub Desktop (versiones gratuitas o académicas) | D42: 1 | E42: 0 | F42: =D42*E42 | G42: Versiones gratuitas o académicas. | H42: Estimado
B43: Subtotal otros costos (desembolso) | F43: =SUM(F39:F42)
B45: 4. RESUMEN DEL PRESUPUESTO ESTIMADO
B46: Concepto | F46: Monto (CLP) | G46: Observación
B47: Desembolso en efectivo (infraestructura + otros costos) | F47: =F35+F43+F70 | G47: Dinero que realmente se paga. Incluye los trámites de la sección 6, hoy registrados en $0 por falta de cotización.
B48: Recurso humano valorizado | F48: =F22 | G48: Referencia de mercado; el equipo no recibe pago.
B49: Subtotal del proyecto | F49: =F47+F48
B50: Contingencia | F50: =F49*$C$10 | G50: Porcentaje definido en los supuestos.
B51: TOTAL PRESUPUESTO ESTIMADO | F51: =F49+F50 | G51: Valor total del proyecto.
B52: Total presupuesto estimado en USD | F52: =F51/$C$6 | G52: Según el tipo de cambio supuesto.
B53: Desembolso en efectivo con contingencia | F53: =F47*(1+$C$10) | G53: Monto mínimo a tener disponible.
B55: 5. PROYECCIÓN ANUAL DE CONTINUIDAD (OPCIÓN B) – REFERENCIAL, NO INCLUIDA EN EL TOTAL
B56: Escenario | C56: Detalle | D56: Meses | E56: Valor mensual (USD) | F56: Costo (CLP) | G56: Observación
B57: Mínimo mensual | C57: Infraestructura productiva | D57: 1 | E57: 100 | F57: =D57*E57*$C$6 | G57: Rango del informe: USD 100 a 120 al mes.
B58: Máximo mensual | C58: Infraestructura productiva | D58: 1 | E58: 120 | F58: =D58*E58*$C$6 | G58: Rango del informe: USD 100 a 120 al mes.
B59: Mínimo anual | C59: Primer año en producción | D59: 12 | E59: 100 | F59: =D59*E59*$C$6 | G59: Proyección de continuidad.
B60: Máximo anual | C60: Primer año en producción | D60: 12 | E60: 120 | F60: =D60*E60*$C$6 | G60: Más comisiones Webpay por transacción (variables, no incluidas).
B63: 6. TRÁMITES DE CONSTITUCIÓN, SII Y PATENTE MUNICIPAL – UN REGISTRO POR CONCEPTO (MONTOS NO COTIZADOS)
B64: Concepto | C64: Naturaleza | D64: Cantidad | E64: Valor unit. (CLP) | F64: Costo (CLP) | G64: Observación | H64: Estado
B65: Constitución de la empresa (EIRL o SpA) y firma ante notario | C65: Trámite legal y notarial | D65: 1 | E65: 0 | F65: =D65*E65 | G65: Registro único del concepto: no se repite en otras filas de esta planilla ni en el Plan de Calidad y de Costos. Sin monto cotizado: se deja en $0 y el total se recalcula al ingresar el valor unitario. | H65: Pendiente de cotización
B66: Inscripción en el Registro de Empresas y Sociedades | C66: Trámite legal | D66: 1 | E66: 0 | F66: =D66*E66 | G66: Supuesto a validar: la inscripción en línea no tendría costo directo para el usuario. Confirmar en el sitio del Registro de Empresas y Sociedades antes de usarlo como referencia. | H66: Pendiente de confirmación
B67: Inicio de actividades ante el SII | C67: Trámite tributario | D67: 1 | E67: 0 | F67: =D67*E67 | G67: Se realiza en línea en el sitio del SII y es requisito para emitir documentos tributarios. Supuesto a validar: no tendría costo directo; si se requiere firma electrónica avanzada, su valor debe cotizarse aparte. | H67: Pendiente de confirmación
B68: Patente municipal (permiso de funcionamiento) | C68: Trámite municipal | D68: 1 | E68: 0 | F68: =D68*E68 | G68: El valor depende de la comuna y del capital declarado. Debe cotizarse en la municipalidad del domicilio comercial. | H68: Pendiente de cotización
B69: Habilitación de facturación y boleta electrónica del SII | C69: Trámite tributario | D69: 1 | E69: 0 | F69: =D69*E69 | G69: Supuesto a validar: el SII ofrece un sistema de facturación electrónica sin costo para el contribuyente. Confirmar antes de darlo por gratuito. No duplica el inicio de actividades. | H69: Pendiente de confirmación
B70: Subtotal trámites (registrado en $0 hasta contar con cotización) | F70: =SUM(F65:F69) | G70: No altera el total estimado mientras no exista un monto cotizado. Al reemplazar los valores unitarios, el desembolso en efectivo (sección 4) se recalcula solo.
B72: 7. RESOLUCIÓN SANITARIA Y ALCANCE DE PRODUCTOS (CONDICIÓN POR VALIDAR CON LA AUTORIDAD SANITARIA)
B73: Alternativa | C73: Alcance de la oferta | D73: Cantidad | E73: Valor unit. (CLP) | F73: Costo (CLP) | G73: Observación | H73: Estado
B74: Alternativa A: oferta limitada a productos sin procesar (recomendada para el MVP) | C74: Frutas, verduras y huevos sin procesar, sin elaboración ni envasado propio | D74: 1 | E74: 0 | F74: =D74*E74 | G74: Efecto analizado: reduce la exposición a exigencias sanitarias de elaboración y etiquetado, pero la necesidad de resolución sanitaria sigue siendo una condición por validar con la SEREMI de Salud, porque depende del tipo de producto, del lugar de acopio y del transporte. No se afirma que sea exigible ni que deje de serlo. | H74: Pendiente de confirmación
B75: Alternativa B: oferta con productos procesados o envasados (no adoptada) | C75: Productos elaborados, envasados o con etiquetado propio | D75: 1 | E75: 0 | F75: =D75*E75 | G75: Aumenta la exposición a exigencias sanitarias del elaborador o de la bodega y a requisitos de etiquetado, con posible inversión y plazos adicionales. | H75: Pendiente de cotización
B76: Etiquetado y transporte de alimentos | C76: Información del producto y condiciones del traslado | D76: 1 | E76: 0 | F76: =D76*E76 | G76: Condición por validar con la autoridad sanitaria y con los requisitos aplicables. No se declara como obligación vigente del MVP ni como gasto comprometido. | H76: Pendiente de confirmación
B77: Subtotal resolución sanitaria y etiquetado (sin cotización) | F77: =SUM(F74:F76) | G77: Se mantiene en $0: no hay cotización ni pronunciamiento de la autoridad sanitaria.
B79: 8. DELIVERY: ALTERNATIVAS EVALUADAS (COSTOS, INGRESOS Y RIESGOS)
B80: Alternativa | C80: Descripción | D80: Cantidad | E80: Valor unit. (CLP) | F80: Costo (CLP) | G80: Observación | H80: Estado
B81: 1. Despacho a cargo del productor (ADOPTADA: línea base del MVP) | C81: El Vendedor entrega el pedido y lo cierra con el código de verificación (RF-007 y RF-025) | D81: 1 | E81: 0 | F81: =D81*E81 | G81: Adoptada porque es la definida en el ERS: no exige inversión ni contratación de terceros y su costo para CuTuCo es $0. En ingresos, la tarifa fija de $3.500 por pedido se descuenta en el Split Payment (RF-014); la contraprestación asociada a esa tarifa está pendiente de confirmación. Riesgo: la entrega depende de la capacidad de cada productor y CuTuCo no tiene respaldo logístico propio. | H81: Confirmado
B82: 2. Reparto externalizado (evaluada, no contratada) | C82: Empresa de reparto o red de repartidores externos con tarifa por entrega | D82: 1 | E82: 0 | F82: =D82*E82 | G82: Sin inversión en flota, con costo variable por pedido y dependencia de terceros. Exige definir si la tarifa fija de $3.500 cubre la entrega. No se contrata durante el MVP. | H82: Pendiente de cotización
B83: 3. Flota y repartidores propios (evaluada, no contratada) | C83: Camiones, furgones o motos propios y repartidores contratados | D83: 1 | E83: 0 | F83: =D83*E83 | G83: Entrega controlada, con inversión inicial y costo fijo mensual (vehículos, combustible, seguros y remuneraciones). No se contrata: depende del volumen real de pedidos y de una decisión formal de inversión. | H83: Pendiente de cotización
B84: Subtotal delivery (alternativas no contratadas, sin cotización) | F84: =SUM(F81:F83) | G84: Criterio de decisión: se adopta la alternativa 1 por ser la línea base del MVP y no generar desembolso. Las alternativas 2 y 3 se reevalúan solo si el volumen de pedidos lo justifica, con cotización y presupuesto aprobado.
B86: 9. CONDICIONES TRIBUTARIAS, COMERCIALES, SANITARIAS Y OPERATIVAS A VALIDAR
B87: Tema | C87: Qué se debe validar y efecto en el presupuesto | G87: Nota | H87: Estado
B88: IVA y boleta electrónica | C88: El ERS define boleta a consumidor final con RUT genérico 66.666.666-6 y factura cuando el comprador es una empresa (B2B). Falta confirmar el tratamiento del IVA sobre la comisión y sobre la tarifa fija por pedido, y si los montos del fee se expresan con o sin IVA. Efecto en el presupuesto: por definir. | G88: Requiere revisión de un contador; pendiente de confirmación. | H88: Pendiente de confirmación
B89: Patente municipal | C89: Aplicabilidad, comuna y base de cálculo del permiso de funcionamiento. Efecto: costo periódico no incluido en el total hasta contar con cotización. | G89: Registrada en la sección 6. | H89: Pendiente de cotización
B90: Resolución sanitaria | C90: Aplicabilidad según el tipo de producto, el lugar de acopio y el transporte. Efecto: podría exigir habilitación de bodega o de sala de proceso, hoy no presupuestada. | G90: Analizada en la sección 7. | H90: Pendiente de confirmación
B91: Etiquetado de productos | C91: Información obligatoria del producto cuando corresponda (origen, peso, fecha y responsable). Efecto: diseño e impresión de etiquetas, hoy no presupuestados. | G91: Condición por validar con la autoridad sanitaria. | H91: Pendiente de confirmación
B92: Transporte de alimentos | C92: Condiciones del traslado (temperatura, envases y limpieza) cuando el despacho lo realiza el productor. Efecto: podría exigir envases o cajas adicionales. | G92: Condición por validar. | H92: Pendiente de confirmación
B93: Comisión de Transbank por transacción | C93: Monto de la comisión y quién la asume en el contrato de Webpay Mall. Efecto: si la asume CuTuCo, se descuenta del ingreso por fee y cambia el punto de equilibrio. | G93: No incluida en el total; pendiente de confirmación. | H93: Pendiente de confirmación
B94: Registro del Código de Comercio Mall | C94: El código se obtiene en el trámite con Transbank y es un paso posterior e independiente de la aprobación de la postulación. Mientras un productor no lo tenga, no puede operar y sus productos no se muestran en el catálogo. | G94: Trámite fuera del flujo principal de la plataforma. | H94: Pendiente de confirmación
B95: Datos bancarios y documentos de postulación | C95: Protección mediante RLS, policies, grants y permisos de almacenamiento de Supabase. Efecto: sin costo adicional durante el MVP. | G95: La inscripción de la cuenta bancaria en Transbank es un trámite externo al flujo de la plataforma; los datos recibidos se protegen con RLS, policies, grants y permisos de almacenamiento. | H95: Confirmado
B96: Suscripción mensual por productor | C96: Precio y adopción del modelo proyectado. Efecto en los ingresos: se modela desde el Año 1 como negocio proyectado. | G96: La facturación de la suscripción no forma parte del MVP. | H96: Fuera del MVP
B97: Delivery | C97: Alternativa adoptada y su efecto en costos, ingresos y riesgos. | G97: Analizada en la sección 8. | H97: Confirmado
B99: 10. ESTADOS DEL PRESUPUESTO Y LEYENDA (APLICA A TODAS LAS FILAS DE ESTA HOJA)
B100: Estado | C100: Significado
B101: Confirmado | C101: Monto o condición verificada en la documentación del proyecto o del proveedor. Incluye los niveles gratuitos, que hoy no generan desembolso.
B102: Estimado | C102: Referencia del equipo para el mercado chileno, sin cotización formal. Puede cambiar al momento de contratar.
B103: Valorizado | C103: Costo de referencia del trabajo del equipo a precio de mercado. No genera desembolso.
B104: Pendiente de cotización | C104: No hay monto sustentable: se registra en $0 y se incorporará al total cuando exista una cotización o un valor oficial.
B105: Pendiente de confirmación | C105: Falta validar la exigibilidad, la aplicabilidad o la cifra antes de comprometer un gasto.
B106: Fuera del MVP | C106: Concepto identificado y modelado como negocio proyectado, pero no activo en esta versión.

Sheet Flujo de Caja y Viabilidad
B1: FLUJO DE CAJA PROYECTADO Y EVALUACIÓN DE VIABILIDAD – CU TUCO
B2: CuTuCo (Cultiva Tu Compra) – Marketplace SaaS B2B2C | Duoc UC Plaza Norte – Ingeniería en Informática
B3: Proyección a 5 años (Año 1 a Año 5) del negocio proyectado. Moneda: pesos chilenos (CLP) nominales.
B4: El MVP académico no factura: esta hoja modela la continuidad del negocio y no forma parte del presupuesto base de las hojas Alto, Medio y Bajo Presupuesto. Los supuestos editables están en amarillo y cada monto indica su estado (sección 6).
B5: La proyección NO incluye captación de clientes (marketing) ni costos variables por transacción: ambos están pendientes de cotización. Por eso el VAN y la TIR deben leerse como un techo referencial, no como un resultado esperado.
B6: 1. SUPUESTOS DEL MODELO (celdas azules con fondo amarillo = editables)
B7: Supuesto | C7: Valor | D7: Observación | H7: Estado
B8: Tipo de cambio (CLP por USD) | C8: ='Bajo Presupuesto'!C6 | D8: Tipo de cambio supuesto del presupuesto base (hoja Bajo Presupuesto, celda C6). | H8: Estimado
B9: Fee de intermediación sobre la venta | C9: 0.05 | D9: Fee base de 5% definido en el ERS (RF-005 y RF-014). Se evalúa en la sección 4. | H9: Confirmado
B10: Tarifa fija por pedido (CLP) | C10: 3500 | D10: Tarifa fija de delivery del ERS (RF-014), descontada en el Split Payment de Webpay Mall. | H10: Confirmado
B11: Ticket promedio por pedido (CLP) | C11: 12000 | D11: Supuesto del equipo: la documentación del proyecto no registra un ticket promedio. Pendiente de confirmación. | H11: Pendiente de confirmación
B12: Suscripción mensual por productor (CLP) | C12: 9900 | D12: Supuesto del equipo. La facturación de la suscripción no forma parte del MVP: se modela como negocio proyectado (Opción B). | H12: Pendiente de confirmación
B13: Adopción de la suscripción en el Año 1 | C13: 0.15 | D13: Supuesto del equipo; la adopción crece por año en la sección 2. | H13: Pendiente de confirmación
B14: Tasa de descuento anual para el VAN | C14: 0.15 | D14: El proyecto no define una tasa de descuento: es un supuesto explícito del equipo. Pendiente de confirmación. | H14: Pendiente de confirmación
B15: Costo de infraestructura productiva (USD por mes) | C15: 110 | D15: Punto medio del rango USD 100 a 120 documentado para la Opción B. | H15: Estimado
B16: Horas de operación y soporte al mes | C16: 40 | D16: Supuesto del equipo para sostener el sistema en producción. | H16: Pendiente de confirmación
B17: Valor hora de operación y soporte (CLP) | C17: ='Bajo Presupuesto'!$E$20 | D17: Valor hora del rol Analista de Procesos del presupuesto base (hoja Bajo Presupuesto, sección 1). | H17: Estimado
B18: Meses por año | C18: 12 | D18: Base de cálculo anual. | H18: Confirmado
B19: Incluir el trabajo valorizado del equipo en la inversión inicial (1 = sí, 0 = no) | C19: 1 | D19: Supuesto del equipo: para un negocio real, construir la plataforma cuesta el trabajo del proyecto. Con 1, la inversión inicial incluye el recurso humano valorizado de la hoja Bajo Presupuesto (celda F48). | H19: Pendiente de confirmación
B21: 2. PROYECCIÓN DE INGRESOS Y COSTOS (AÑO 1 A AÑO 5)
B22: Concepto | C22: Año 1 | D22: Año 2 | E22: Año 3 | F22: Año 4 | G22: Año 5 | H22: Observación
B23: Productores activos (supuesto) | C23: 15 | D23: 40 | E23: 80 | F23: 130 | G23: 200 | H23: Supuesto de penetración del equipo; pendiente de confirmación.
B24: Pedidos por productor al mes (supuesto) | C24: 4 | D24: 5 | E24: 6 | F24: 6 | G24: 7 | H24: Supuesto del equipo; pendiente de confirmación.
B25: Adopción de la suscripción (supuesto) | C25: 0.15 | D25: 0.25 | E25: 0.35 | F25: 0.4 | G25: 0.45 | H25: Supuesto del equipo; pendiente de confirmación.
B26: Pedidos al año | C26: =C23*C24*$C$18 | D26: =D23*D24*$C$18 | E26: =E23*E24*$C$18 | F26: =F23*F24*$C$18 | G26: =G23*G24*$C$18 | H26: Productores activos × pedidos por productor al mes × meses del año.
B27: Ticket promedio (CLP) | C27: =$C$11 | D27: =$C$11 | E27: =$C$11 | F27: =$C$11 | G27: =$C$11 | H27: Supuesto del modelo (celda C11).
B28: Venta total del marketplace (GMV) | C28: =C26*C27 | D28: =D26*D27 | E28: =E26*E27 | F28: =F26*F27 | G28: =G26*G27 | H28: Valor transado por los productores; no es ingreso de CuTuCo.
B29: INGRESOS DE CU TUCO
B30: Fee de intermediación (5% del GMV) | C30: =C28*$C$9 | D30: =D28*$C$9 | E30: =E28*$C$9 | F30: =F28*$C$9 | G30: =G28*$C$9 | H30: Ingreso por el fee base de 5% (RF-005 y RF-014).
B31: Tarifa fija por pedido ($3.500) | C31: =C26*$C$10 | D31: =D26*$C$10 | E31: =E26*$C$10 | F31: =F26*$C$10 | G31: =G26*$C$10 | H31: Se descuenta en el Split Payment de Webpay Mall (RF-014).
B32: Suscripción mensual de productores (fuera del MVP) | C32: =C23*C25*$C$12*$C$18 | D32: =D23*D25*$C$12*$C$18 | E32: =E23*E25*$C$12*$C$18 | F32: =F23*F25*$C$12*$C$18 | G32: =G23*G25*$C$12*$C$18 | H32: Facturación proyectada: no forma parte del MVP y no se cobra en el período académico.
B33: Total de ingresos | C33: =SUM(C30:C32) | D33: =SUM(D30:D32) | E33: =SUM(E30:E32) | F33: =SUM(F30:F32) | G33: =SUM(G30:G32) | H33: Suma de las tres líneas de ingreso.
B34: COSTOS RECURRENTES
B35: Infraestructura productiva | C35: =$C$15*$C$18*$C$8 | D35: =$C$15*$C$18*$C$8 | E35: =$C$15*$C$18*$C$8 | F35: =$C$15*$C$18*$C$8 | G35: =$C$15*$C$18*$C$8 | H35: USD 110 al mes según el supuesto; equivale al rango documentado de USD 100 a 120.
B36: Operación y soporte | C36: =$C$16*$C$17*$C$18 | D36: =$C$16*$C$17*$C$18 | E36: =$C$16*$C$17*$C$18 | F36: =$C$16*$C$17*$C$18 | G36: =$C$16*$C$17*$C$18 | H36: Horas al mes valorizadas al valor hora del supuesto.
B37: Captación de productores y compradores (marketing) | C37: 0 | D37: 0 | E37: 0 | F37: 0 | G37: 0 | H37: Pendiente de cotización: no se incorpora al flujo. Su ausencia explica por qué el VAN y la TIR son un techo referencial.
B38: Delivery asumido por CuTuCo | C38: 0 | D38: 0 | E38: 0 | F38: 0 | G38: 0 | H38: Escenario base: el despacho lo realiza el productor y no genera costo para CuTuCo. Alternativas evaluadas en la sección 8 de las hojas de presupuesto.
B39: Trámites y obligaciones por validar | C39: 0 | D39: 0 | E39: 0 | F39: 0 | G39: 0 | H39: Pendientes de cotización: no se incorporan al flujo hasta contar con el monto.
B40: Comisión de Transbank por transacción | C40: 0 | D40: 0 | E40: 0 | F40: 0 | G40: 0 | H40: Pendiente de confirmación: la comisión del contrato de Webpay Mall podría descontarse del ingreso por fee.
B41: Total de costos recurrentes | C41: =SUM(C35:C40) | D41: =SUM(D35:D40) | E41: =SUM(E35:E40) | F41: =SUM(F35:F40) | G41: =SUM(G35:G40) | H41: Costos que se repiten cada año.
B42: Flujo del período (ingresos − costos) | C42: =C33-C41 | D42: =D33-D41 | E42: =E33-E41 | F42: =F33-F41 | G42: =G33-G41 | H42: Resultado del año, antes de la inversión inicial.
B44: 3. INVERSIÓN INICIAL Y FLUJO DE CAJA (AÑO 0 A AÑO 5)
B45: Período | C45: Inversión inicial (CLP) | D45: Ingresos (CLP) | E45: Costos (CLP) | F45: Flujo del período (CLP) | G45: Flujo acumulado (CLP) | H45: Observación
B46: Año 0 | C46: ='Bajo Presupuesto'!$F$53+$C$19*'Bajo Presupuesto'!$F$48 | D46: 0 | E46: 0 | F46: =-C46 | G46: =F46 | H46: Inversión inicial: desembolso en efectivo con contingencia del escenario base más el trabajo valorizado del equipo, según el interruptor de la sección 1.
B47: Año 1 | D47: =C33 | E47: =C41 | F47: =D47-E47 | G47: =G46+F47 | H47: Ingresos y costos recurrentes del año según la sección 2.
B48: Año 2 | D48: =D33 | E48: =D41 | F48: =D48-E48 | G48: =G47+F48
B49: Año 3 | D49: =E33 | E49: =E41 | F49: =D49-E49 | G49: =G48+F49
B50: Año 4 | D50: =F33 | E50: =F41 | F50: =D50-E50 | G50: =G49+F50
B51: Año 5 | D51: =G33 | E51: =G41 | F51: =D51-E51 | G51: =G50+F51
B53: VAN con la tasa de descuento del supuesto (Año 0 a Año 5) | C53: =F46+NPV($C$14,F47:F51) | D53: Valor actual neto del flujo proyectado con la tasa de la celda C14, que es un supuesto. | H53: Pendiente de confirmación
B54: TIR del flujo de caja (Año 0 a Año 5) | C54: =IRR(F46:F51) | D54: Tasa interna de retorno del flujo proyectado (Año 0 a Año 5). | H54: Pendiente de confirmación
B55: Recuperación de la inversión (payback) | C55: =IF(MAX(G46:G51)<0,"No recupera en el horizonte de 5 años",INDEX($B$46:$B$51,MATCH(TRUE,INDEX(G46:G51>=0,0),0))) | D55: Primer período en que el flujo acumulado deja de ser negativo. | H55: Pendiente de confirmación
B56: VAN con tasa de descuento de 10% (referencia) | C56: =F46+NPV(0.1,F47:F51) | D56: Sensibilidad: el proyecto no define la tasa de descuento. | H56: Estimado
B57: VAN con tasa de descuento de 20% (referencia) | C57: =F46+NPV(0.2,F47:F51) | D57: Sensibilidad: el proyecto no define la tasa de descuento. | H57: Estimado
B58: Inversión inicial de referencia: escenario Medio (solo desembolso) | C58: ='Medio Presupuesto'!$F$54 | D58: Si se adoptara el escenario Medio, el desembolso inicial sería mayor. | H58: Estimado
B59: Inversión inicial de referencia: escenario Alto (solo desembolso) | C59: ='Alto Presupuesto'!$F$55 | D59: Si se adoptara el escenario Alto, el desembolso inicial sería mayor. | H59: Estimado
B61: 4. ANÁLISIS DEL FEE DE REFERENCIA DEL 5% (AÑO 1)
B62: Concepto | C62: Valor | D62: Observación | H62: Estado
B63: Ingreso anual por fee de intermediación (Año 1) | C63: =C30 | D63: Ingreso del fee de 5% sobre el GMV del Año 1. | H63: Estimado
B64: Costos recurrentes anuales (Año 1) | C64: =C41 | D64: Infraestructura productiva más operación y soporte. | H64: Estimado
B65: Cobertura del fee sobre los costos recurrentes (Año 1) | C65: =C63/C64 | D65: Proporción de los costos recurrentes que cubriría el fee por sí solo. | H65: Estimado
B66: GMV anual necesario para cubrir los costos solo con el fee | C66: =C64/$C$9 | D66: Con un fee de 5%, este es el GMV mínimo anual para cubrir los costos recurrentes. | H66: Estimado
B67: Pedidos al mes necesarios para cubrir los costos solo con el fee | C67: =C66/$C$11/$C$18 | D67: Con el ticket promedio supuesto (celda C11). | H67: Estimado
B68: Fee equivalente si el único ingreso fuera el fee (Año 1) | C68: =C64/C28 | D68: Porcentaje del GMV que se necesitaría para cubrir los costos recurrentes del Año 1. | H68: Estimado
B69: Ingreso anual por la tarifa fija de $3.500 (Año 1) | C69: =C31 | D69: Aporte de la tarifa fija por pedido, que es la mayor fuente de ingreso del modelo. | H69: Estimado
B70: Ingreso total del Año 1 (fee + tarifa + suscripción) | C70: =C33 | D70: Comparación con los costos recurrentes del mismo año. | H70: Estimado
B71: Conclusión del análisis del fee | C71: ="Con el fee del 5% por sí solo, el modelo no cubre los costos recurrentes del Año 1: el fee aporta cerca del "&TEXT(C65,"0.0%")&" de ellos y, para cubrirlos solo con el fee, haría falta un GMV anual de $"&TEXT(C66,"#,##0")&" (unos "&TEXT(C67,"#,##0")&" pedidos al mes), es decir un fee equivalente a "&TEXT(C68,"0.0%")&" de la venta. El modelo se sostiene porque la tarifa fija de $3.500 por pedido aporta $"&TEXT(C69,"#,##0")&" en el Año 1, más que el propio fee. Recomendación sujeta a decisión del equipo: mantener el fee base de 5% durante el MVP y, antes de pasar a producción, evaluar un fee entre 7% y 8% del GMV o un ajuste de la tarifa fija por pedido, con cotización previa de la comisión de Transbank y del costo real de operación."
B73: 5. CONCLUSIONES Y RECOMENDACIONES (SUJETAS A DECISIÓN)
B74: Viabilidad referencial: el VAN y la TIR dependen de supuestos no confirmados (ticket promedio, penetración de productores, pedidos por productor al mes, precio y adopción de la suscripción, tasa de descuento y valor del trabajo del equipo). Cualquier cambio en ellos cambia el resultado y debe registrarse como decisión formal; las filas de sensibilidad muestran el efecto de la tasa de descuento.
B75: Techo referencial: la proyección no incluye captación de clientes (marketing), costos variables por transacción ni el crecimiento del equipo de operación. Con esos costos, hoy pendientes de cotización, el VAN y la TIR serían menores. Por eso el resultado se presenta como un techo y no como un resultado esperado.
B76: Ingresos: el fee de 5% y la tarifa fija de $3.500 por pedido provienen del ERS (RF-005 y RF-014) y son las únicas fuentes de ingreso del MVP. La suscripción mensual por productor se modela como negocio proyectado y su facturación no forma parte del MVP.
B77: Costos: la infraestructura productiva se estima en USD 100 a 120 al mes y el delivery no genera costo para CuTuCo en el MVP porque lo asume el productor. Los trámites de constitución, SII, patente municipal y resolución sanitaria están pendientes de cotización y hoy se registran en $0.
B78: Riesgo principal: la mayor parte del ingreso depende de la tarifa fija por pedido y no del fee, de modo que una caída en el número de pedidos afecta directamente el resultado. El punto de equilibrio se alcanza con el volumen indicado en la sección 4.
B79: Decisiones pendientes: el ajuste del fee, el precio de la suscripción y la evaluación de la logística (reparto externalizado o flota propia) requieren cotizaciones formales y presupuesto aprobado antes de comprometer cualquier gasto.
B81: 6. ESTADOS DEL PRESUPUESTO Y LEYENDA
B82: Estado | C82: Significado
B83: Confirmado | C83: Monto o condición verificada en la documentación del proyecto o del proveedor. Incluye los niveles gratuitos, que hoy no generan desembolso.
B84: Estimado | C84: Referencia del equipo para el mercado chileno, sin cotización formal. Puede cambiar al momento de contratar.
B85: Valorizado | C85: Costo de referencia del trabajo del equipo a precio de mercado. No genera desembolso.
B86: Pendiente de cotización | C86: No hay monto sustentable: se registra en $0 y se incorporará al total cuando exista una cotización o un valor oficial.
B87: Pendiente de confirmación | C87: Falta validar la exigibilidad, la aplicabilidad o la cifra antes de comprometer un gasto.
B88: Fuera del MVP | C88: Concepto identificado y modelado como negocio proyectado, pero no activo en esta versión.
